computercraft/__init__.py
computercraft/back.lua
computercraft/errors.py
computercraft/lua.py
computercraft/rproc.py
computercraft/ser.py
computercraft/server.py
computercraft/sess.py
computercraft/subapis/__init__.py
computercraft/subapis/_pkg.py
computercraft/subapis/base.py
computercraft/subapis/colors.py
computercraft/subapis/commands.py
computercraft/subapis/disk.py
computercraft/subapis/fs.py
computercraft/subapis/gps.py
computercraft/subapis/help.py
computercraft/subapis/keys.py
computercraft/subapis/mixins.py
computercraft/subapis/multishell.py
computercraft/subapis/os.py
computercraft/subapis/paintutils.py
computercraft/subapis/parallel.py
computercraft/subapis/peripheral.py
computercraft/subapis/pocket.py
computercraft/subapis/rednet.py
computercraft/subapis/redstone.py
computercraft/subapis/settings.py
computercraft/subapis/shell.py
computercraft/subapis/term.py
computercraft/subapis/textutils.py
computercraft/subapis/turtle.py
computercraft/subapis/window.py
robocraft-1.1.7.dist-info/METADATA
robocraft-1.1.7.dist-info/WHEEL
robocraft-1.1.7.dist-info/entry_points.txt
robocraft-1.1.7.dist-info/top_level.txt
robocraft-1.1.7.dist-info/RECORD
